ascend/auth/auth.py
ascend/auth/session.py
ascend/external/protoc_gen_swagger/options/annotations_pb2.py
ascend/external/protoc_gen_swagger/options/openapiv2_pb2.py
ascend/external/python_path.py
ascend/log/__init__.py
ascend/openapi/openapi/openapi_client/api/__init__.py
ascend/openapi/openapi/openapi_client/api/ascend_api.py
ascend/openapi/openapi/openapi_client/api_client.py
ascend/openapi/openapi/openapi_client/configuration.py
ascend/openapi/openapi/openapi_client/exceptions.py
ascend/openapi/openapi/openapi_client/rest.py
ascend/openapi/python_path.py
ascend/protos/api/api_pb2.py
ascend/protos/api/api_pb2.py.bak
ascend/protos/ascend/ascend_pb2.py
ascend/protos/component/component_pb2.py
ascend/protos/connection/connection_pb2.py
ascend/protos/content_encoding/content_encoding_pb2.py
ascend/protos/core/core_pb2.py
ascend/protos/environment/environment_pb2.py
ascend/protos/expression/expression_pb2.py
ascend/protos/external/external_pb2.py
ascend/protos/fault/fault_pb2.py
ascend/protos/format/format_pb2.py
ascend/protos/function/function_pb2.py
ascend/protos/io/io_pb2.py
ascend/protos/metrics/metrics_pb2.py
ascend/protos/operator/operator_pb2.py
ascend/protos/pattern/pattern_pb2.py
ascend/protos/preview/preview_pb2.py
ascend/protos/resource/resource_pb2.py
ascend/protos/resources/resources_pb2.py
ascend/protos/schema/schema_pb2.py
ascend/protos/service/spark_manager/spark_manager_pb2.py
ascend/protos/task/task_pb2.py
ascend/protos/text/text_pb2.py
ascend/protos/worker/worker_pb2.py
ascend/sdk/applier.py
ascend/sdk/builder.py
ascend/sdk/cli.py
ascend/sdk/client.py
ascend/sdk/common.py
ascend/sdk/connection_value.py
ascend/sdk/definitions.py
ascend/sdk/drd/credentials.py
ascend/sdk/drd/jinja.py
ascend/sdk/drd/resource.py
ascend/sdk/field.py
ascend/sdk/poetry/pyproject.toml
ascend/sdk/render.py
ascend/sdk/templates/v1/common.jinja
ascend/sdk/templates/v1/component.jinja
ascend/sdk/templates/v1/data_service.jinja
ascend/sdk/templates/v1/dataflow.jinja
ascend_io_sdk-0.2.65.dist-info/METADATA
ascend_io_sdk-0.2.65.dist-info/WHEEL
ascend_io_sdk-0.2.65.dist-info/entry_points.txt
ascend_io_sdk-0.2.65.dist-info/RECORD
