Metadata-Version: 2.1
Name: ascend-io-sdk
Version: 0.2.65
Summary: The Ascend.io SDK for Python
Home-page: https://www.ascend.io
License: Apache-2.0
Keywords: ascend,pipeline,data,automation,platform
Author: Ascend.io Engineering
Author-email: support@ascend.io
Maintainer: Ascend.io Engineering
Maintainer-email: support@ascend.io
Requires-Python: >=3.7,<4.0
Classifier: Intended Audience :: Developers
Classifier: License :: OSI Approved :: Apache Software License
Classifier: Programming Language :: Python :: 3
Classifier: Programming Language :: Python :: 3.7
Classifier: Programming Language :: Python :: 3.8
Classifier: Programming Language :: Python :: 3.9
Classifier: Programming Language :: Python :: 3.10
Classifier: Programming Language :: Python :: 3.11
Classifier: Programming Language :: Python :: 3.12
Classifier: Programming Language :: Python :: 3 :: Only
Classifier: Topic :: Software Development :: Build Tools
Classifier: Topic :: Software Development :: Libraries :: Python Modules
Requires-Dist: Jinja2 (>=3.1.1,<4.0.0)
Requires-Dist: backoff (>=1.10.0,<2.0.0)
Requires-Dist: chardet (==3.0.4)
Requires-Dist: glog (>=0.3.1,<0.4.0)
Requires-Dist: googleapis-common-protos (==1.56.4)
Requires-Dist: idna (==2.10)
Requires-Dist: networkx (>=2.5,<3.0)
Requires-Dist: protobuf (==3.20.*)
Requires-Dist: python-dateutil (>=2.8.1,<3.0.0)
Requires-Dist: requests (>=2.25.1,<3.0.0)
Requires-Dist: retry (>=0.9.2,<0.10.0)
Requires-Dist: six (==1.16.0)
Requires-Dist: toml (==0.10.1)
Requires-Dist: urllib3 (>=1.26.5,<2.0.0)
Project-URL: Ascend.io, https://www.ascend.io
Project-URL: Ascend Developer, https://developer.ascend.io
Project-URL: Documentation, https://developer.ascend.io/docs/python-sdk
